[{"siap":"12345","dataContratacao":"","bolsasCadastradas":[],"nome":"marlon","idade":0,"CPF":"123.456.789-00","dataNascimento":"09/02/2003","senha":"72ab994fa2eb426c051ef59cad617750bfe06d7cf6311285ff79c19c32afd236","telefone":"","dataDeInscricao":"Jun 21, 2023, 12:46:31 AM"},
{"siap":"12345","dataContratacao":"","bolsasCadastradas":[],"nome":"igor","idade":0,"CPF":"123.456.789-00","dataNascimento":"09/02/2002","senha":"72ab994fa2eb426c051ef59cad617750bfe06d7cf6311285ff79c19c32afd236","telefone":"","dataDeInscricao":"Jun 21, 2023, 12:48:43 AM"},
{"siap":"12345","dataContratacao":"","bolsasCadastradas":[],"nome":"marlon","idade":0,"CPF":"123.456.789-00","dataNascimento":"09/09/2002","senha":"ef797c8118f02dfb649607dd5d3f8c7623048c9c063d532cc95c5ed7a898a64f","telefone":"","dataDeInscricao":"Jun 21, 2023, 1:35:43 AM"}]